Qomolangma/__init__.py
Qomolangma/__version__.py
Qomolangma/cli.py
Qomolangma/logo.png
Qomolangma-0.0.1.data/data/LICENSE
Qomolangma-0.0.1.dist-info/LICENSE
Qomolangma-0.0.1.dist-info/METADATA
Qomolangma-0.0.1.dist-info/WHEEL
Qomolangma-0.0.1.dist-info/entry_points.txt
Qomolangma-0.0.1.dist-info/top_level.txt
Qomolangma-0.0.1.dist-info/RECORD
