Metadata-Version: 2.1
Name: Qomolangma
Version: 0.0.1
Summary: Awesome NLP tool you are waiting for ✨
Home-page: https://github.com/szj2ys/Qomolangma
Author: szj
Author-email: szj2ys@qq.com
License: MIT
Platform: UNKNOWN
Classifier: License :: OSI Approved :: MIT License
Classifier: Programming Language :: Python :: 3.6
Classifier: Programming Language :: Python :: 3.7
Classifier: Programming Language :: Python :: 3.8
Classifier: Programming Language :: Python :: 3.9
Requires-Python: >=3.6.0
License-File: LICENSE
Requires-Dist: pandas
Requires-Dist: tensorflow (~=2.6)
Requires-Dist: click
Requires-Dist: click-help-colors
